[{"id":875674272,"name":"StreetComplete","description":"Inspektions-app til Android.","documentation":"https://wiki.openstreetmap.org/wiki/Da:StreetComplete","community":{"issueTracker":"https://github.com/streetcomplete/StreetComplete/issues","githubDiscussions":"streetcomplete/StreetComplete","slack":"https://osmus.slack.com/archives/CRCUH32G5"},"source":[{"name":"Wikidata","id":"Q56221667","language":"da","url":"http://www.wikidata.org/entity/Q56221667"},{"name":"Software","language":"da","id":"Da:StreetComplete","url":"https://wiki.openstreetmap.org/wiki/Da:StreetComplete","lastChange":"2026-01-21T07:11:54Z"}]},{"id":302672956,"name":"Every Door","description":"Power mapper's mobile editor for maintaining amenities on OSM.","documentation":"https://wiki.openstreetmap.org/wiki/Da:Every Door","community":{},"source":[{"name":"Software","language":"da","id":"Da:Every Door","url":"https://wiki.openstreetmap.org/wiki/Da:Every Door","lastChange":"2024-10-27T10:31:50Z"}]},{"id":2608327,"name":"uMap","description":"Lav dit eget kort, tilføj markører og meget mere.","documentation":"https://wiki.openstreetmap.org/wiki/Da:UMap","community":{"matrix":"#umap:matrix.org"},"source":[{"name":"Software","language":"da","id":"Da:UMap","url":"https://wiki.openstreetmap.org/wiki/Da:UMap","lastChange":"2025-06-23T21:23:36Z"}]},{"id":1513544470,"name":"Navit","description":"","documentation":"","community":{},"source":[{"name":"Wikidata","id":"Q1305715","language":"da","url":"http://www.wikidata.org/entity/Q1305715"}]},{"id":1221193415,"name":"QGIS","description":"","documentation":"","community":{},"source":[{"name":"Wikidata","id":"Q1329181","language":"da","url":"http://www.wikidata.org/entity/Q1329181"}]},{"id":139646831,"name":"MoNav","description":"","documentation":"","community":{},"source":[{"name":"Wikidata","id":"Q17011387","language":"da","url":"http://www.wikidata.org/entity/Q17011387"}]},{"id":2061387786,"name":"MAPS.ME","description":"","documentation":"","community":{},"source":[{"name":"Wikidata","id":"Q17280647","language":"da","url":"http://www.wikidata.org/entity/Q17280647"}]},{"id":1757813068,"name":"iD","description":"","documentation":"","community":{},"source":[{"name":"Wikidata","id":"Q18275868","language":"da","url":"http://www.wikidata.org/entity/Q18275868"}]},{"id":1545336785,"name":"GraphHopper","description":"","documentation":"","community":{},"source":[{"name":"Wikidata","id":"Q20017427","language":"da","url":"http://www.wikidata.org/entity/Q20017427"}]},{"id":830455704,"name":"Mapillary","description":"","documentation":"","community":{},"source":[{"name":"Wikidata","id":"Q26757498","language":"da","url":"http://www.wikidata.org/entity/Q26757498"}]},{"id":2000999168,"name":"PeakFinder","description":"","documentation":"","community":{},"source":[{"name":"Wikidata","id":"Q28925511","language":"da","url":"http://www.wikidata.org/entity/Q28925511"}]},{"id":1244795925,"name":"osm2pgsql","description":"","documentation":"","community":{},"source":[{"name":"Wikidata","id":"Q28975314","language":"da","url":"http://www.wikidata.org/entity/Q28975314"}]},{"id":837447154,"name":"OsmAnd","description":"open source navigationsapp med offline kort","documentation":"","community":{},"source":[{"name":"Wikidata","id":"Q3087512","language":"da","url":"http://www.wikidata.org/entity/Q3087512"}]},{"id":1621834020,"name":"Sophox","description":"","documentation":"","community":{},"source":[{"name":"Wikidata","id":"Q55840137","language":"da","url":"http://www.wikidata.org/entity/Q55840137"}]},{"id":164728912,"name":"Danmarks svampeatlas","description":"","documentation":"","community":{},"source":[{"name":"Wikidata","id":"Q59654144","language":"da","url":"http://www.wikidata.org/entity/Q59654144"}]},{"id":1748335418,"name":"Natural Atlas","description":"","documentation":"","community":{},"source":[{"name":"Wikidata","id":"Q88769787","language":"da","url":"http://www.wikidata.org/entity/Q88769787"}]},{"id":856624173,"name":"GRAMPS","description":"","documentation":"","community":{},"source":[{"name":"Wikidata","id":"Q902166","language":"da","url":"http://www.wikidata.org/entity/Q902166"}]},{"id":1479970798,"name":"SAH Archipedia","description":"","documentation":"","community":{},"source":[{"name":"Wikidata","id":"Q97063049","language":"da","url":"http://www.wikidata.org/entity/Q97063049"}]}]