[{"id":856624173,"name":"","subtitle":"","description":"open source software computer genealogie","documentation":"","community":{},"source":[{"name":"Wikidata","id":"Q902166","language":"zea","url":"http://www.wikidata.org/entity/Q902166","lastChange":"2026-01-26T19:51:38Z"}]},{"id":1442493873,"name":"GraphHopper","subtitle":"","description":"open source routeringsengine","documentation":"","community":{},"source":[{"name":"Wikidata","id":"Q20017427","language":"zea","url":"http://www.wikidata.org/entity/Q20017427","lastChange":"2025-10-14T16:14:04Z"}]}]